fastent
