Metadata-Version: 1.1
Name: fastent
Version: 0.7.3
Summary: Automated Custom NER tool
Home-page: https://github.com/fastent/fastent
Author: Erik Arakelyan
Author-email: erikarakelyan1997@gmail.com
License: UNKNOWN
Download-URL: https://github.com/fastent/fastent/archive/0.7.tar.gz
Keywords: NER,Annotation,Contextualization
Platform: UNKNOWN
